setup.cfg
setup.py
ol_commons/__init__.py
ol_commons/auth.py
ol_commons/errors.py
ol_commons/helpers.py
ol_commons/constants/__init__.py
ol_commons/constants/general.py
ol_commons/constants/http_codes.py
ol_commons/constants/messages.py
ol_commons_dev.egg-info/PKG-INFO
ol_commons_dev.egg-info/SOURCES.txt
ol_commons_dev.egg-info/dependency_links.txt
ol_commons_dev.egg-info/requires.txt
ol_commons_dev.egg-info/top_level.txt